LICENSE
MANIFEST.in
README.rst
setup.py
django_metaredirect.egg-info/PKG-INFO
django_metaredirect.egg-info/SOURCES.txt
django_metaredirect.egg-info/dependency_links.txt
django_metaredirect.egg-info/not-zip-safe
django_metaredirect.egg-info/requires.txt
django_metaredirect.egg-info/top_level.txt
metaredirect/__init__.py
metaredirect/helpers.py
metaredirect/models.py
metaredirect/views.py
metaredirect/templates/metaredirect/redirect.txt
metaredirect/templatetags/__init__.py
metaredirect/templatetags/escaping.py
metaredirect/tests/__init__.py
metaredirect/tests/tests.py