Metadata-Version: 1.0
Name: django-metaredirect
Version: 0.1.3
Summary: META-tag and JavaScript based generic redirect views for maintaining HTTP referrers.
Home-page: http://github.com/disqus/django-metaredirect/
Author: ted kaemming
Author-email: ted@disqus.com
License: Apache License 2.0
Platform: UNKNOWN
